odoo10_addon_connector_magento-10.0.1.0.0.99.dev42-py3.8-nspkg.pth
odoo/addons/connector_magento/AUTHORS
odoo/addons/connector_magento/README.rst
odoo/addons/connector_magento/__init__.py
odoo/addons/connector_magento/__manifest__.py
odoo/addons/connector_magento/exception.py
odoo/addons/connector_magento/components/__init__.py
odoo/addons/connector_magento/components/backend_adapter.py
odoo/addons/connector_magento/components/binder.py
odoo/addons/connector_magento/components/core.py
odoo/addons/connector_magento/components/deleter.py
odoo/addons/connector_magento/components/exporter.py
odoo/addons/connector_magento/components/importer.py
odoo/addons/connector_magento/components/line_builder.py
odoo/addons/connector_magento/components/mapper.py
odoo/addons/connector_magento/data/connector_magento_data.xml
odoo/addons/connector_magento/doc/Makefile
odoo/addons/connector_magento/doc/conf.py
odoo/addons/connector_magento/doc/core
odoo/addons/connector_magento/doc/index.rst
odoo/addons/connector_magento/doc/make.bat
odoo/addons/connector_magento/doc/_static/img/LogicSupply_Orange_260x80_transparent.png
odoo/addons/connector_magento/doc/_static/img/akretion_logo.png
odoo/addons/connector_magento/doc/_static/img/c2c_square_baseline_192.jpg
odoo/addons/connector_magento/doc/_static/img/logo-debonix.jpg
odoo/addons/connector_magento/doc/_static/img/sync-workflow.png
odoo/addons/connector_magento/doc/_templates/layout.html
odoo/addons/connector_magento/doc/_themes/.gitignore
odoo/addons/connector_magento/doc/api/api_components.rst
odoo/addons/connector_magento/doc/api/api_exception.rst
odoo/addons/connector_magento/doc/api/api_models.rst
odoo/addons/connector_magento/doc/guides/connector_checkpoint.rst
odoo/addons/connector_magento/doc/guides/installation_guide.rst
odoo/addons/connector_magento/doc/guides/key_questions.rst
odoo/addons/connector_magento/doc/guides/monitor_resolve_jobs.rst
odoo/addons/connector_magento/doc/guides/tutorial_customize.rst
odoo10_addon_connector_magento-10.0.1.0.0.99.dev42.dist-info/METADATA
odoo10_addon_connector_magento-10.0.1.0.0.99.dev42.dist-info/WHEEL
odoo10_addon_connector_magento-10.0.1.0.0.99.dev42.dist-info/namespace_packages.txt
odoo10_addon_connector_magento-10.0.1.0.0.99.dev42.dist-info/top_level.txt
odoo10_addon_connector_magento-10.0.1.0.0.99.dev42.dist-info/RECORD
