Metadata-Version: 2.1
Name: odoo10-addon-connector-magento
Version: 10.0.1.0.0.99.dev42
Summary: Magento Connector
Home-page: http://www.odoo-magento-connector.com
Author: Camptocamp,Akretion,Sodexis,Odoo Community Association (OCA)
Author-email: support@odoo-community.org
License: AGPL-3
Platform: UNKNOWN
Classifier: Programming Language :: Python
Classifier: Framework :: Odoo
Classifier: Framework :: Odoo :: 10.0
Classifier: License :: OSI Approved :: GNU Affero General Public License v3
Requires-Python: ~=2.7
Requires-Dist: magento
Requires-Dist: odoo10-addon-base-technical-user
Requires-Dist: odoo10-addon-connector-ecommerce
Requires-Dist: odoo10-addon-product-multi-category
Requires-Dist: odoo <10.1dev,>=10.0
